{
  "发票-增值税专用发票": [
    "发票代码",
    "发票号码",
    "开票日期",
    "发票类型",
    "购买方名称",
    "购买方纳税人识别号",
    "购买方地址电话",
    "购买方开户行及账号",
    "销售方名称",
    "销售方纳税人识别号",
    "销售方地址电话",
    "销售方开户行及账号",
    "货物或服务名称",
    "规格型号",
    "单位",
    "数量",
    "单价",
    "金额",
    "税率",
    "税额",
    "合计金额",
    "合计税额",
    "备注",
    "校验码",
    "二维码"
  ],
  "发票-增值税普通发票": [
    "发票代码",
    "发票号码",
    "开票日期",
    "发票类型",
    "购买方名称",
    "购买方纳税人识别号",
    "销售方名称",
    "销售方纳税人识别号",
    "货物或服务名称",
    "规格型号",
    "单位",
    "数量",
    "单价",
    "金额",
    "税率",
    "税额",
    "含税金额",
    "备注",
    "校验码",
    "二维码"
  ],
  "发票-电子发票": [
    "发票代码",
    "发票号码",
    "开票日期",
    "发票类型",
    "购买方名称",
    "购买方纳税人识别号",
    "销售方名称",
    "销售方纳税人识别号",
    "货物或服务名称",
    "金额",
    "税率",
    "税额",
    "含税金额",
    "备注",
    "校验码",
    "二维码",
    "防伪码"
  ],
  "发票-机动车销售统一发票": [
    "发票代码",
    "发票号码",
    "开票日期",
    "购买方名称",
    "购买方身份证号",
    "销售方名称",
    "销售方纳税人识别号",
    "车辆类型",
    "厂牌型号",
    "产地",
    "合格证号",
    "车架号",
    "发动机号",
    "价税合计",
    "税率",
    "税额",
    "备注",
    "校验码"
  ],
  "发票-通行费发票": [
    "发票代码",
    "发票号码",
    "开票日期",
    "车牌号",
    "金额",
    "税率",
    "税额",
    "价税合计",
    "收费单位",
    "备注",
    "二维码"
  ],
  "发票-火车票/机票行程单": [
    "票据类型",
    "票号",
    "开票日期",
    "乘车人/旅客姓名",
    "身份证号",
    "出发站/出发机场",
    "到达站/到达机场",
    "出发时间",
    "到达时间",
    "金额",
    "税率",
    "税额",
    "座位等级/舱位",
    "票价币种",
    "校验码"
  ],
  "发票-出租车发票": [
    "发票代码",
    "发票号码",
    "开票日期",
    "车牌号",
    "上车时间",
    "下车时间",
    "金额",
    "公里数",
    "单价",
    "备注",
    "二维码"
  ]
}
